potions/__init__.py
potions/__main__.py
potions/calibrate.py
potions/common_types.py
potions/database.py
potions/forcing.py
potions/hydro.py
potions/interfaces.py
potions/math.py
potions/model.py
potions/objective_functions.py
potions/reaction_network.py
potions/reactive_transport.py
potions/utils.py
potions/tests/__init__.py
potions/tests/test_equilibrium.py
potions/tests/test_model.py
potions/tests/test_reactive_transport.py
potions/tests/test_utils.py
potions/tests/test_zones.py
potions/tests/utils.py
potions_model-0.0.1.dist-info/METADATA
potions_model-0.0.1.dist-info/WHEEL
potions_model-0.0.1.dist-info/top_level.txt
potions_model-0.0.1.dist-info/RECORD
