Metadata-Version: 2.4
Name: potions-model
Version: 0.0.1
Summary: A simple and flexible hydrologic modeling package
Author-email: Andrew Vierbicher <acv5255@psu.edu>
Requires-Python: >=3.10
Requires-Dist: numpy
Requires-Dist: scipy
Requires-Dist: pandas
Requires-Dist: matplotlib
Requires-Dist: emcee
